COPYING
COPYING.LESSER
MANIFEST.in
README.rst
download_lt.py
language-check
run_doctest.py
setup.cfg
setup.py
test.bash
test.py
language_check/__init__.py
language_check/__main__.py
language_check/console_mode.py
language_check/main.py
language_check/which.py
language_check.egg-info/PKG-INFO
language_check.egg-info/SOURCES.txt
language_check.egg-info/dependency_links.txt
language_check.egg-info/not-zip-safe
language_check.egg-info/top_level.txt
language_check/backports/__init__.py
language_check/backports/subprocess.py